[
  {
    "originalTitle": "Suspected suicide attacks kill at least 23 in north-east Nigeria",
    "title": "Suspected suicide attacks kill at least 23 in north-east Nigeria",
    "content": "Multiple blasts struck some of the Maiduguri's busiest locations on Monday evening.",
    "summary": "Error rewriting content.",
    "whyMatters": "Unknown",
    "category": "technology",
    "date": "2026-03-17T10:44:43.781Z",
    "image": "https://image.pollinations.ai/prompt/Suspected%20suicide%20attacks%20kill%20at%20least%2023%20in%20north-east%20Nigeria%20realistic%20news%20photography%20context%20Technology%20high%20quality?width=800&height=400&nologo=true",
    "urlSlug": "suspected-suicide-attacks-kill-at-least-23-in-north-east-nigeria",
    "originalLink": "https://www.bbc.com/news/articles/c4gqnjjy9edo?at_medium=RSS&at_campaign=rss"
  },
  {
    "originalTitle": "'Fire came from the sky and burned them' - life on the brink of civil war in South Sudan",
    "title": "Big News from South Sudan: People Moving to Be Safe!",
    "content": "Hello, amazing kids! Your friend, the African News Reporter, is here with some important news from our wonderful continent, Africa. Today, we're talking about a country called South Sudan, and some very brave people who live there.\n\n<h3>A Sad Story in South Sudan</h3>\nImagine your home. Your cozy bed, your favorite toys, your kitchen where yummy food is made. Now, imagine if you had to leave all of it, very quickly. That's what is happening to many, many people in a special part of South Sudan called Jonglei State.\n\nA lot of people, about 50,000 of them, are being told to leave their houses right now. Can you imagine how many that is? It's like all the children in many, many schools, and all their families, all together! They are packing a few things and going to find a safe place.\n\nDid you know? 50,000 is a super big number! It’s more people than can fit in a big football stadium! Each one is a real person, with a family and friends, just like you.\n\n<h3>Why Are People Leaving Their Homes?</h3>\nThis is happening because there might be a big, big fight. Sometimes, people in a country can't agree on important things. When they can't talk and make friends again, they might start to fight. This kind of big fight, when it's between people in the same country, is sometimes called a 'civil war.'\n\nThe soldiers, who are supposed to keep everyone safe, are warning that this big fight could start very soon. Because of this danger, they are telling everyone to move away, so they don't get hurt. It's a very serious warning to keep everyone out of harm's way.\n\nSimple explanation: Imagine you and your friend have a disagreement. Usually, you talk it out and become friends again. But if you couldn't, and started to argue and push each other, that's like a tiny fight. A country's fight is much, much bigger and can be very dangerous and loud. People leave to avoid these dangers.\n\n<h3>Where is South Sudan?</h3>\nSouth Sudan is a beautiful country right here in Africa! Africa is a giant continent, full of amazing animals like elephants, giraffes, and zebras, and wonderful people who love to sing and dance.\n\nSouth Sudan has big green fields, tall trees, and the famous Nile River flowing through it. Jonglei is a special area within South Sudan, just like your town or city is a part of your country. It's usually a peaceful place where families live and children go to school and play.\n\nDid you know? South Sudan is one of the newest countries in the world! It became its own country not too long ago, in 2011, which means it’s only a little bit older than some of you!\n\n<h3>What Happens When People Leave Their Homes?</h3>\nWhen people have to leave their homes very quickly, it's called 'fleeing' or becoming 'displaced.' It means they have to leave everything they know and love behind.\n\nThey try to take only the most important things: a few clothes, maybe some food, and special items like a blanket or a toy if they have space. Then they walk, or sometimes ride in a car or a boat, to try and find a safer place. It must be very sad and a little bit scary to leave your school, your friends, and your playground behind.\n\nThey hope to find a place where there are no loud noises from fighting, and where they can feel safe and calm again. It's like going on a very unplanned trip, but you don't know when you can go back home.\n\n<h3>Who Helps People Who Have to Leave?</h3>\nWhen people are in trouble, there are always kind people who try to help. Families help each other, and neighbors help neighbors. But there are also special helpers from all around the world!\n\nThese special helpers are sometimes called 'humanitarian workers' or 'aid workers.' They bring food, clean water, warm blankets, and medicine to places where people need help. They try to set up safe places, like big tents or buildings, where people can stay for a while until it's safe to go home.\n\nDid you know? Many, many children and grown-ups all over the world care about the children and families in South Sudan. They send donations and prayers, and work hard to make sure everyone is safe, healthy, and happy again.\n\n<h3>Wishing for Peace</h3>\nEveryone, especially us here at African News for Kids, hopes that the fighting stops very, very soon in South Sudan. We want all the people there to live in peace and safety.\n\nPeace means no fighting, no loud noises, just everyone being kind, sharing, and helping each other. We hope that all the children can go back to their schools, play with their friends, and sleep soundly in their own beds without any worries. It's so important that people can talk to each other and find ways to be friends again, instead of fighting.\n\nSimple explanation: Peace is like when everyone is happy and calm. No one is arguing, no one is hurting anyone, and everyone can just enjoy living together. It's the best way to live!\n\n<h3>Let's Send Our Love</h3>\nLet's all send our kind thoughts and wishes to all the children and families in South Sudan. We hope they find safety and can go back to their homes very, very soon. Remember, even when things are tough, there are always good people trying to help, and there is always hope for a better tomorrow.\n\nWe wish for blue skies, happy days, and lots of peace for everyone in South Sudan. Stay safe and keep being kind, little friends!",
    "summary": "About 50,000 people in Jonglei State, South Sudan, are being told to leave their homes for safety because there might be a big fight, and many people are helping them find safe places to stay.",
    "whyMatters": "This is important because many children and families are leaving their homes, which is very sad and scary, and we want them to be safe and happy again, living in peace without any fighting.",
    "category": "world",
    "date": "2026-03-17T10:45:08.280Z",
    "image": "https://image.pollinations.ai/prompt/Big%20News%20from%20South%20Sudan%3A%20People%20Moving%20to%20Be%20Safe!%20realistic%20news%20photography%20context%20World%20News%20high%20quality?width=800&height=400&nologo=true",
    "urlSlug": "big-news-from-south-sudan-people-moving-to-be-safe",
    "originalLink": "https://www.bbc.com/news/articles/cx2g4v9mzxro?at_medium=RSS&at_campaign=rss"
  },
  {
    "originalTitle": "Russia agrees to stop using Kenyan recruits in Ukraine conflict, Kenya says",
    "title": "Russia agrees to stop using Kenyan recruits in Ukraine conflict, Kenya says",
    "content": "Some 1,000 Kenyans are believed to have recruited to fight in Ukraine - many say they were lured under false pretences.",
    "summary": "Error rewriting content.",
    "whyMatters": "Unknown",
    "category": "world",
    "date": "2026-03-17T10:45:13.401Z",
    "image": "https://image.pollinations.ai/prompt/Russia%20agrees%20to%20stop%20using%20Kenyan%20recruits%20in%20Ukraine%20conflict%2C%20Kenya%20says%20realistic%20news%20photography%20context%20World%20News%20high%20quality?width=800&height=400&nologo=true",
    "urlSlug": "russia-agrees-to-stop-using-kenyan-recruits-in-ukraine-conflict-kenya-says",
    "originalLink": "https://www.bbc.com/news/articles/cev7rdwmky9o?at_medium=RSS&at_campaign=rss"
  },
  {
    "originalTitle": "Could the Iran war trigger a global recession?",
    "title": "Big News from Far Away: Why Keeping the World Peaceful Helps Us All!",
    "content": "Jambo, amazing young friends! It's your friendly African news reporter here, bringing you super important news from around our wonderful world. My name is Auntie Zola, and I'm so happy to talk to all you bright sparks in Class 2 today!\n\nSometimes, things happen far, far away that can still touch our lives, even right here at home. Today, we're going to talk about something happening in a country called Iran, which is very, very far from Africa. Don't worry, we'll learn about it together, and it's not scary when we understand it.\n\n<h3>What's Happening in a Land Called Iran?</h3>\n\nImagine you have a group of friends, but sometimes they don't get along very well. They might argue, or even have a big fight. Well, in Iran, some grown-ups are having a big disagreement, and sadly, sometimes this leads to fighting, which we call a 'conflict' or even a 'war'.\n\nWhen people are fighting, it makes it very hard for things to move around safely. It's like if there was a big football game happening in the middle of the road – cars and buses wouldn't be able to pass easily, right?\n\n<h3>What is 'Black Gold' and Why is it Important?</h3>\n\nNow, let's talk about something super important that comes from Iran and other places: oil! You might have heard grown-ups talk about 'petrol' for cars. Petrol is made from oil. Oil is a thick, dark liquid that we find deep, deep under the ground.\n\nDid you know? Oil is sometimes called 'black gold' because it's so valuable! It helps our world run.\n\nOil isn't just for cars. It helps buses take us to school, it helps power stations make electricity for our lights and TVs, and it even helps big machines in factories make our toys, clothes, and yummy snacks!\n\n<h3>When Oil Gets Tricky to Get</h3>\n\nBecause there's fighting in Iran, it's becoming very hard to get this 'black gold' out of the ground and send it to other countries that need it. Think of it like a shop that sells your favorite sweets. If the road to the sweet shop is blocked, it's hard for new sweets to arrive, isn't it?\n\nWhen it's hard to get oil, there's less of it going around in the world. And when there's less of something important, its price usually goes up. This means it becomes more expensive.\n\n<h3>How Does Expensive Oil Affect Us?</h3>\n\nEven though Iran is far away, if oil gets more expensive, it can affect many, many people around the globe, and sometimes, even here in Africa.\n\n*   **Bus rides and cars:** If petrol costs more, your parents might pay more to fill up their car, or bus tickets might get a little more expensive to cover the cost.\n*   **Electricity:** The power stations that make electricity for our homes often use oil or other fuels that get more expensive when oil does. So, our electricity bills might go up.\n*   **Our food and toys:** Think about your favorite banana or a new toy. They have to travel to get to you! Big ships and trucks carry them, and those ships and trucks use fuel (made from oil). If the fuel costs more, then the banana or the toy might cost a little more too, because it cost more to bring them here.\n\nDid you know? Many plastic items, like some of your toys and water bottles, are also made from oil!\n\n<h3>What is a 'Recession'? (A Simple Idea)</h3>\n\nGrown-ups sometimes use a big word called 'recession'. It sounds complicated, but let's make it simple. Imagine your family has a pot of money. If things like petrol, food, and electricity all become much more expensive, your family might have less money left in that pot for other things, like new clothes or fun days out.\n\nIf this happens to many, many families in many different countries all at the same time, grown-ups call it a 'recession'. It means that people everywhere might have a little less money, and it might be harder for businesses to grow or for grown-ups to find jobs.\n\nDon't worry, many clever people and leaders in different countries are always working hard to make sure this doesn't happen, or if it does, to help everyone through it.\n\n<h3>Who are the US, China, and Europe?</h3>\n\nThe news also talks about 'risks' for places like the US, China, and Europe. These are very big countries and groups of countries far away. They buy a lot of oil to keep their factories running, their lights on, and their cars moving.\n\nIf they can't get enough oil, or if it costs too much, it can make things difficult for all the people living there, just like it can affect us.\n\nDid you know? The United States (US) is a country in North America, China is a huge country in Asia, and Europe is a continent with many countries like France, Germany, and Italy!\n\n<h3>Why Peace Matters Everywhere</h3>\n\nSo, what does all this teach us? It shows us that we are all connected in this big, beautiful world. What happens in one country can actually have a ripple effect, like dropping a stone in a pond, and reach other countries.\n\nThat's why it's so important for people to try and get along, to talk things through, and to choose peace instead of fighting. When there is peace, oil can flow smoothly, things can be made and sent easily, and families everywhere can have an easier time buying the things they need.\n\n<h3>What Can You Do?</h3>\n\nYou might be thinking, 'I'm just a kid, what can I do?' Well, you can do a lot!\n\n*   **Be kind:** Start by being kind to your friends and family. Peace begins with us!\n*   **Save energy:** Remember to switch off lights when you leave a room. Every little bit helps!\n*   **Learn:** Keep learning about the world. The more we understand, the better we can help.\n\nThank you for listening, my wonderful young friends! Remember to always be curious, be kind, and know that even when big challenges happen, people are working hard to make the world a better, more peaceful place for everyone. Until next time, stay curious and keep shining bright!",
    "summary": "Fighting in a faraway country called Iran is making it harder to get oil, which means things like petrol and electricity might get more expensive for everyone, showing us how important peace is around the world.",
    "whyMatters": "This matters because when fighting happens far away, it can make important things like petrol, electricity, and even toys cost more for families everywhere, showing us that what happens in one place can affect people all around the world.",
    "category": "world",
    "date": "2026-03-17T10:45:32.999Z",
    "image": "https://image.pollinations.ai/prompt/Big%20News%20from%20Far%20Away%3A%20Why%20Keeping%20the%20World%20Peaceful%20Helps%20Us%20All!%20realistic%20news%20photography%20context%20World%20News%20high%20quality?width=800&height=400&nologo=true",
    "urlSlug": "big-news-from-far-away-why-keeping-the-world-peaceful-helps-us-all",
    "originalLink": "https://www.aljazeera.com/video/counting-the-cost/2026/3/17/could-the-iran-war-trigger-a-global-recession?traffic_source=rss"
  },
  {
    "originalTitle": "Blood tech: The UK ambassador, the sex offender, Palantir, and Gaza",
    "title": "Blood tech: The UK ambassador, the sex offender, Palantir, and Gaza",
    "content": "Despite its public objections to Israel’s actions, the UK is buying spyware developed and tested on Palestinians.",
    "summary": "Error rewriting content.",
    "whyMatters": "Unknown",
    "category": "world",
    "date": "2026-03-17T10:45:38.114Z",
    "image": "https://image.pollinations.ai/prompt/Blood%20tech%3A%20The%20UK%20ambassador%2C%20the%20sex%20offender%2C%20Palantir%2C%20and%20Gaza%20realistic%20news%20photography%20context%20World%20News%20high%20quality?width=800&height=400&nologo=true",
    "urlSlug": "blood-tech-the-uk-ambassador-the-sex-offender-palantir-and-gaza",
    "originalLink": "https://www.aljazeera.com/news/2026/3/17/blood-tech-the-uk-ambassador-the-sex-offender-palantir-and-gaza?traffic_source=rss"
  },
  {
    "originalTitle": "Israel says Iran’s security chief Larijani has been killed",
    "title": "Israel says Iran’s security chief Larijani has been killed",
    "content": "Israel’s Defence Minister Israel Katz says Ali Larijani, Iran’s security chief, has been killed in an Israeli strike.",
    "summary": "Error rewriting content.",
    "whyMatters": "Unknown",
    "category": "politics",
    "date": "2026-03-17T10:45:43.229Z",
    "image": "https://image.pollinations.ai/prompt/Israel%20says%20Iran%E2%80%99s%20security%20chief%20Larijani%20has%20been%20killed%20realistic%20news%20photography%20context%20Politics%20high%20quality?width=800&height=400&nologo=true",
    "urlSlug": "israel-says-irans-security-chief-larijani-has-been-killed",
    "originalLink": "https://www.aljazeera.com/video/newsfeed/2026/3/17/israel-says-irans-security-chief-larijani-has-been-killed?traffic_source=rss"
  },
  {
    "originalTitle": "Trump seeks to delay meeting with Xi in China",
    "title": "Trump seeks to delay meeting with Xi in China",
    "content": "The escalating war in Iran has overshadowed many of the US' foreign policy objectives",
    "summary": "Error rewriting content.",
    "whyMatters": "Unknown",
    "category": "world",
    "date": "2026-03-17T10:45:49.183Z",
    "image": "https://image.pollinations.ai/prompt/Trump%20seeks%20to%20delay%20meeting%20with%20Xi%20in%20China%20realistic%20news%20photography%20context%20World%20News%20high%20quality?width=800&height=400&nologo=true",
    "urlSlug": "trump-seeks-to-delay-meeting-with-xi-in-china",
    "originalLink": "https://www.bbc.com/news/articles/cn9e0z7v3nxo?at_medium=RSS&at_campaign=rss"
  },
  {
    "originalTitle": "Trump says presidents 'should not have learning disabilities' as he mocks Newsom's dyslexia",
    "title": "Trump says presidents 'should not have learning disabilities' as he mocks Newsom's dyslexia",
    "content": "The National Center for Learning Disabilities said it was \"disturbed\" by the president's remarks.",
    "summary": "Error rewriting content.",
    "whyMatters": "Unknown",
    "category": "politics",
    "date": "2026-03-17T10:45:54.295Z",
    "image": "https://image.pollinations.ai/prompt/Trump%20says%20presidents%20'should%20not%20have%20learning%20disabilities'%20as%20he%20mocks%20Newsom's%20dyslexia%20realistic%20news%20photography%20context%20Politics%20high%20quality?width=800&height=400&nologo=true",
    "urlSlug": "trump-says-presidents-should-not-have-learning-disabilities-as-he-mocks-newsoms-dyslexia",
    "originalLink": "https://www.bbc.com/news/articles/c4gjnwmm984o?at_medium=RSS&at_campaign=rss"
  },
  {
    "originalTitle": "Dozens killed in air strike on Kabul rehab centre blamed on Pakistan",
    "title": "Dozens killed in air strike on Kabul rehab centre blamed on Pakistan",
    "content": "The BBC visited the facility and saw more than 30 bodies being carried out on stretchers.",
    "summary": "Error rewriting content.",
    "whyMatters": "Unknown",
    "category": "technology",
    "date": "2026-03-17T10:45:59.389Z",
    "image": "https://image.pollinations.ai/prompt/Dozens%20killed%20in%20air%20strike%20on%20Kabul%20rehab%20centre%20blamed%20on%20Pakistan%20realistic%20news%20photography%20context%20Technology%20high%20quality?width=800&height=400&nologo=true",
    "urlSlug": "dozens-killed-in-air-strike-on-kabul-rehab-centre-blamed-on-pakistan",
    "originalLink": "https://www.bbc.com/news/articles/c4g8n7e0l40o?at_medium=RSS&at_campaign=rss"
  },
  {
    "originalTitle": "Arsenal trial and self-doubt: Valverde's journey to Real legend",
    "title": "Arsenal trial and self-doubt: Valverde's journey to Real legend",
    "content": "Rejected by Arsenal as a teenager, Federico Valverde has transformed himself into a Real Madrid legend - and was the main man in their Champions League win over Manchester City last week.",
    "summary": "Error rewriting content.",
    "whyMatters": "Unknown",
    "category": "sports",
    "date": "2026-03-17T10:46:04.686Z",
    "image": "https://image.pollinations.ai/prompt/Arsenal%20trial%20and%20self-doubt%3A%20Valverde's%20journey%20to%20Real%20legend%20realistic%20news%20photography%20context%20Sports%20high%20quality?width=800&height=400&nologo=true",
    "urlSlug": "arsenal-trial-and-self-doubt-valverdes-journey-to-real-legend",
    "originalLink": "https://www.bbc.com/sport/football/articles/cd9g12yl111o?at_medium=RSS&at_campaign=rss"
  },
  {
    "originalTitle": "Ramsey left out again for Wales' World Cup play-offs",
    "title": "Ramsey left out again for Wales' World Cup play-offs",
    "content": "Captain Aaron Ramsey is left out of the Wales squad for this month's World Cup play-offs, casting further doubt over his future.",
    "summary": "Error rewriting content.",
    "whyMatters": "Unknown",
    "category": "world",
    "date": "2026-03-17T10:46:09.802Z",
    "image": "https://image.pollinations.ai/prompt/Ramsey%20left%20out%20again%20for%20Wales'%20World%20Cup%20play-offs%20realistic%20news%20photography%20context%20World%20News%20high%20quality?width=800&height=400&nologo=true",
    "urlSlug": "ramsey-left-out-again-for-wales-world-cup-play-offs",
    "originalLink": "https://www.bbc.com/sport/football/articles/cwyk0znkdz5o?at_medium=RSS&at_campaign=rss"
  },
  {
    "originalTitle": "How Chelsea signed a star team with hidden payments",
    "title": "How Chelsea signed a star team with hidden payments",
    "content": "Chelsea have been hit with a Premier League record fine of £10.75m and handed a suspended transfer ban. Here's what the written reasons said.",
    "summary": "Error rewriting content.",
    "whyMatters": "Unknown",
    "category": "sports",
    "date": "2026-03-17T10:46:14.915Z",
    "image": "https://image.pollinations.ai/prompt/How%20Chelsea%20signed%20a%20star%20team%20with%20hidden%20payments%20realistic%20news%20photography%20context%20Sports%20high%20quality?width=800&height=400&nologo=true",
    "urlSlug": "how-chelsea-signed-a-star-team-with-hidden-payments",
    "originalLink": "https://www.bbc.com/sport/football/articles/cn48e171zlvo?at_medium=RSS&at_campaign=rss"
  }
]