[
  {
    "originalTitle": "'Massive' numbers killed by gunmen in latest Nigeria attack, senator tells BBC",
    "title": "'Massive' numbers killed by gunmen in latest Nigeria attack, senator tells BBC",
    "content": "Suspected Islamist militants reportedly seized control of a village for two days before being forced out by troops and air strikes.",
    "summary": "Error rewriting content.",
    "whyMatters": "Unknown",
    "category": "world",
    "date": "2026-03-07T04:58:53.512Z",
    "image": "https://image.pollinations.ai/prompt/'Massive'%20numbers%20killed%20by%20gunmen%20in%20latest%20Nigeria%20attack%2C%20senator%20tells%20BBC%20realistic%20news%20photography%20context%20World%20News%20high%20quality?width=800&height=400&nologo=true",
    "urlSlug": "massive-numbers-killed-by-gunmen-in-latest-nigeria-attack-senator-tells-bbc",
    "originalLink": "https://www.bbc.com/news/articles/c1d69z3p9g2o?at_medium=RSS&at_campaign=rss"
  },
  {
    "originalTitle": "Ugandan students who fled Iran air strikes recall 'ground trembling' ",
    "title": "Brave Ugandan Students are Safe and Sound!",
    "content": "<h3>Hello, Wonderful Friends!</h3>\n\nHello, wonderful friends from across Africa! It’s your friendly reporter, here to share an important story with you. Have you ever been far from home? Maybe at a friend's house or on a school trip? Well, imagine being super far away, in a country called Iran. Some of our bright students from Uganda were there, learning new things and making new friends. But then, something a little scary happened.\n\n<h3>The Big, Scary Shakes!</h3>\n\nOne night, in that faraway land, our friends, the students, heard some really loud noises. Like the loudest thunder you’ve ever heard, but even bigger and closer! The ground started to shake, tremble, and rumble. Imagine your bed shaking like a toy car, or the walls of your room wobbling! That’s how some of our friends felt when the ground moved under their feet. It was a very scary moment for everyone.\n\nThese scary noises were because of something grown-ups call 'air strikes.' It means there were loud events happening in the sky, far away, that made big booms and made the ground rumble. It was not a nice feeling at all. Our Ugandan friends felt worried and longed for the safety of their homes.\n\nDid you know? Iran is a country very, very far from Uganda! It’s on a different continent, across many lands and seas. Flying there takes many, many hours on an airplane!\n\n<h3>Help Arrives from Home!</h3>\n\nWhen our grown-ups in Uganda heard about the scary sounds, they didn't waste a minute! The government of Uganda, which is like a big team of helpers who look after everyone in the country, wanted to make sure every single Ugandan student was safe. They knew how important it was for our students to feel secure and protected.\n\nSo, guess what they did? They quickly made special arrangements! They wanted to bring all the students back home, where it's safe and sound, surrounded by their families and friends. It's like when your parents come to pick you up quickly when you're feeling unwell at school, because they want you to be safe and happy.\n\nDid you know? A government is like a big team of helpers who work hard to keep everyone in a country safe, healthy, and happy! They make sure there are schools, hospitals, and good roads for everyone.\n\n<h3>The Long Trip Home</h3>\n\nSo, airplanes were quickly made ready! Imagine packing your bags very quickly and getting ready for a very, very long airplane ride. Many students were so happy to go home. They missed their families, their favourite Ugandan food, and the warm sunshine of Uganda.\n\nThey flew high above the clouds, over many different countries and big, blue oceans, until finally, they could see the green lands of Uganda again. Oh, the joy of seeing familiar faces, of hugging their mums and dads, must have been wonderful! They were so happy to be back on African soil, safe and sound with their loved ones.\n\nDid you know? Uganda is sometimes called the 'Pearl of Africa' because it's so beautiful, with lots of green places, amazing animals, and friendly people!\n\n<h3>But Some Friends Stayed!</h3>\n\nBut here’s a curious thing, friends! Not everyone came back right away. Some of our brave students thought very carefully about their choices. Even after the scary noises and the offer to come home, they decided to stay in Iran for a little longer.\n\nWhy did they choose to stay? Well, they were learning important lessons there, things for their future jobs, like how to be doctors, engineers, or scientists! They had big dreams and important studies to finish. And they felt strong and brave enough to keep learning, even after the scary sounds. They felt safe enough to continue their studies.\n\nTheir parents and the Ugandan government understood and respected their choice. Everyone wants our young people to be smart, strong, and to achieve their dreams! It shows that sometimes, even when things are difficult, we can be brave and continue to work towards our goals.\n\n<h3>Learning from Our Friends</h3>\n\nThis story tells us many things, friends. It tells us how brave and strong our Ugandan friends are. They faced something scary, and they made important choices for their future. It also shows us that even when we are far away from home, our family and our country always care about us very, very much.\n\nThey want us to be safe, to learn, and to grow into amazing young people. Being brave doesn't mean you're not scared; it means you keep going and do what you need to do, even when you feel a little bit scared.\n\nDid you know? It's okay to feel scared sometimes, but being brave means you try your best to overcome that fear and keep going!\n\n<h3>A Big Cheer for Our Students!</h3>\n\nSo, remember, friends! No matter where you are, it's good to feel safe. And it's wonderful that our grown-ups, our governments, always try their very best to keep us out of harm's way and help us achieve our dreams. Let's send a big cheer to all our Ugandan student friends!\n\nWhether they are back in the sunny lands of Uganda, or still learning far away in Iran, we wish them all the best. They are showing us all how to be brave, smart, and strong. Keep shining, amazing African kids!",
    "summary": "Some brave Ugandan students who were studying in Iran experienced scary loud noises, but their government helped many come home, while others bravely chose to stay and finish their studies.",
    "whyMatters": "This story matters because it shows how our governments help us, how brave young people can be, and that it's important to feel safe wherever we are.",
    "category": "world",
    "date": "2026-03-07T04:59:15.514Z",
    "image": "https://image.pollinations.ai/prompt/Brave%20Ugandan%20Students%20are%20Safe%20and%20Sound!%20realistic%20news%20photography%20context%20World%20News%20high%20quality?width=800&height=400&nologo=true",
    "urlSlug": "brave-ugandan-students-are-safe-and-sound",
    "originalLink": "https://www.bbc.com/news/articles/cn8zd3q3090o?at_medium=RSS&at_campaign=rss"
  },
  {
    "originalTitle": "The young women who fought in Ethiopia's last civil war and don't want to see another one",
    "title": "The young women who fought in Ethiopia's last civil war and don't want to see another one",
    "content": "Female fighters recall how the conflict in the northern Tigray destroyed their lives, as fears grow that fighting could resume.",
    "summary": "Error rewriting content.",
    "whyMatters": "Unknown",
    "category": "world",
    "date": "2026-03-07T04:59:20.651Z",
    "image": "https://image.pollinations.ai/prompt/The%20young%20women%20who%20fought%20in%20Ethiopia's%20last%20civil%20war%20and%20don't%20want%20to%20see%20another%20one%20realistic%20news%20photography%20context%20World%20News%20high%20quality?width=800&height=400&nologo=true",
    "urlSlug": "the-young-women-who-fought-in-ethiopias-last-civil-war-and-dont-want-to-see-another-one",
    "originalLink": "https://www.bbc.com/news/articles/cyv959eyjgjo?at_medium=RSS&at_campaign=rss"
  },
  {
    "originalTitle": "Why Yemen’s Houthis are staying out of Israel-US fight with Iran – for now",
    "title": "Why Yemen’s Houthis are staying out of Israel-US fight with Iran – for now",
    "content": "Yemen's Houthi leadership cautious, fearing Israeli retaliation following past air strikes and leadership losses.",
    "summary": "Error rewriting content.",
    "whyMatters": "Unknown",
    "category": "technology",
    "date": "2026-03-07T04:59:26.043Z",
    "image": "https://image.pollinations.ai/prompt/Why%20Yemen%E2%80%99s%20Houthis%20are%20staying%20out%20of%20Israel-US%20fight%20with%20Iran%20%E2%80%93%20for%20now%20realistic%20news%20photography%20context%20Technology%20high%20quality?width=800&height=400&nologo=true",
    "urlSlug": "why-yemens-houthis-are-staying-out-of-israel-us-fight-with-iran-for-now",
    "originalLink": "https://www.aljazeera.com/news/2026/3/7/why-yemens-houthis-are-staying-out-of-israel-us-fight-with-iran-for-now?traffic_source=rss"
  },
  {
    "originalTitle": "Anti-aircraft fire seen in eastern Lebanon amid Israeli incursion",
    "title": "Anti-aircraft fire seen in eastern Lebanon amid Israeli incursion",
    "content": "Apparent anti-aircraft fire was seen in the Bekaa Valley of eastern Lebanon amid reports of an attempted Israeli attack.",
    "summary": "Error rewriting content.",
    "whyMatters": "Unknown",
    "category": "technology",
    "date": "2026-03-07T04:59:31.178Z",
    "image": "https://image.pollinations.ai/prompt/Anti-aircraft%20fire%20seen%20in%20eastern%20Lebanon%20amid%20Israeli%20incursion%20realistic%20news%20photography%20context%20Technology%20high%20quality?width=800&height=400&nologo=true",
    "urlSlug": "anti-aircraft-fire-seen-in-eastern-lebanon-amid-israeli-incursion",
    "originalLink": "https://www.aljazeera.com/video/newsfeed/2026/3/7/anti-aircraft-fire-seen-in-eastern-lebanon-amid-israeli-incursion?traffic_source=rss"
  },
  {
    "originalTitle": "Massive explosions, fires from US-Israeli strikes on Tehran",
    "title": "Massive explosions, fires from US-Israeli strikes on Tehran",
    "content": "Massive explosions and fires were seen across Tehran as US-Israeli strikes pummelled targets in the Iranian capital.",
    "summary": "Error rewriting content.",
    "whyMatters": "Unknown",
    "category": "world",
    "date": "2026-03-07T04:59:36.315Z",
    "image": "https://image.pollinations.ai/prompt/Massive%20explosions%2C%20fires%20from%20US-Israeli%20strikes%20on%20Tehran%20realistic%20news%20photography%20context%20World%20News%20high%20quality?width=800&height=400&nologo=true",
    "urlSlug": "massive-explosions-fires-from-us-israeli-strikes-on-tehran",
    "originalLink": "https://www.aljazeera.com/video/newsfeed/2026/3/7/massive-explosions-fires-from-us-israeli-strikes-on-tehran?traffic_source=rss"
  },
  {
    "originalTitle": "Trump demands 'unconditional surrender' from Iran as Putin speaks with Iran's president",
    "title": "Trump demands 'unconditional surrender' from Iran as Putin speaks with Iran's president",
    "content": "The president also calls on Tehran to pick new leaders who are \"acceptable\" to the White House after six days of war.",
    "summary": "Error rewriting content.",
    "whyMatters": "Unknown",
    "category": "world",
    "date": "2026-03-07T04:59:41.782Z",
    "image": "https://image.pollinations.ai/prompt/Trump%20demands%20'unconditional%20surrender'%20from%20Iran%20as%20Putin%20speaks%20with%20Iran's%20president%20realistic%20news%20photography%20context%20World%20News%20high%20quality?width=800&height=400&nologo=true",
    "urlSlug": "trump-demands-unconditional-surrender-from-iran-as-putin-speaks-with-irans-president",
    "originalLink": "https://www.bbc.com/news/articles/c5yq82k1wk8o?at_medium=RSS&at_campaign=rss"
  },
  {
    "originalTitle": "Flight paths squeezed as Iran conflict closes more airspace ",
    "title": "Flight paths squeezed as Iran conflict closes more airspace ",
    "content": "A drone attack on Azerbaijan has narrowed choices for airlines scrambling to respond to disruption in the Gulf.",
    "summary": "Error rewriting content.",
    "whyMatters": "Unknown",
    "category": "technology",
    "date": "2026-03-07T04:59:46.912Z",
    "image": "https://image.pollinations.ai/prompt/Flight%20paths%20squeezed%20as%20Iran%20conflict%20closes%20more%20airspace%20%20realistic%20news%20photography%20context%20Technology%20high%20quality?width=800&height=400&nologo=true",
    "urlSlug": "flight-paths-squeezed-as-iran-conflict-closes-more-airspace",
    "originalLink": "https://www.bbc.com/news/articles/crrx1jgr4jjo?at_medium=RSS&at_campaign=rss"
  },
  {
    "originalTitle": "Armed robots take to the battlefield in Ukraine war",
    "title": "Armed robots take to the battlefield in Ukraine war",
    "content": "Ukraine has embarked on a programme to deploy armed robots on the battlefield against Russian forces.",
    "summary": "Error rewriting content.",
    "whyMatters": "Unknown",
    "category": "world",
    "date": "2026-03-07T04:59:52.043Z",
    "image": "https://image.pollinations.ai/prompt/Armed%20robots%20take%20to%20the%20battlefield%20in%20Ukraine%20war%20realistic%20news%20photography%20context%20World%20News%20high%20quality?width=800&height=400&nologo=true",
    "urlSlug": "armed-robots-take-to-the-battlefield-in-ukraine-war",
    "originalLink": "https://www.bbc.com/news/articles/c62662gzlp8o?at_medium=RSS&at_campaign=rss"
  },
  {
    "originalTitle": "'Slot needs something to keep him in a job' - could the FA Cup be it?",
    "title": "'Slot needs something to keep him in a job' - could the FA Cup be it?",
    "content": "Despite a torrid Premier League campaign, could winning the FA Cup keep Liverpool manager Arne Slot in a job?",
    "summary": "Error rewriting content.",
    "whyMatters": "Unknown",
    "category": "jobs",
    "date": "2026-03-07T04:59:57.350Z",
    "image": "https://image.pollinations.ai/prompt/'Slot%20needs%20something%20to%20keep%20him%20in%20a%20job'%20-%20could%20the%20FA%20Cup%20be%20it%3F%20realistic%20news%20photography%20context%20Jobs%20high%20quality?width=800&height=400&nologo=true",
    "urlSlug": "slot-needs-something-to-keep-him-in-a-job-could-the-fa-cup-be-it",
    "originalLink": "https://www.bbc.com/sport/football/articles/cp814p8j3kdo?at_medium=RSS&at_campaign=rss"
  },
  {
    "originalTitle": "Who is to blame for Spurs' chaotic descent towards relegation?",
    "title": "Who is to blame for Spurs' chaotic descent towards relegation?",
    "content": "BBC Sport's chief football writer Phil McNulty examines who - or what - is to blame for Spurs' crisis as they fight to avoid relegation.",
    "summary": "Error rewriting content.",
    "whyMatters": "Unknown",
    "category": "sports",
    "date": "2026-03-07T05:00:02.508Z",
    "image": "https://image.pollinations.ai/prompt/Who%20is%20to%20blame%20for%20Spurs'%20chaotic%20descent%20towards%20relegation%3F%20realistic%20news%20photography%20context%20Sports%20high%20quality?width=800&height=400&nologo=true",
    "urlSlug": "who-is-to-blame-for-spurs-chaotic-descent-towards-relegation",
    "originalLink": "https://www.bbc.com/sport/football/articles/cwy9xd2y392o?at_medium=RSS&at_campaign=rss"
  },
  {
    "originalTitle": "Joao Pedro same level as Haaland and Kane - Rosenior",
    "title": "Joao Pedro same level as Haaland and Kane - Rosenior",
    "content": "Chelsea head coach Liam Rosenior says striker Joao Pedro belongs in the same \"category\" as world‑class forwards Erling Haaland, Harry Kane and Kylian Mbappe.",
    "summary": "Error rewriting content.",
    "whyMatters": "Unknown",
    "category": "world",
    "date": "2026-03-07T05:00:07.649Z",
    "image": "https://image.pollinations.ai/prompt/Joao%20Pedro%20same%20level%20as%20Haaland%20and%20Kane%20-%20Rosenior%20realistic%20news%20photography%20context%20World%20News%20high%20quality?width=800&height=400&nologo=true",
    "urlSlug": "joao-pedro-same-level-as-haaland-and-kane-rosenior",
    "originalLink": "https://www.bbc.com/sport/football/articles/c4gjxp9x8klo?at_medium=RSS&at_campaign=rss"
  }
]